cadbuildr/__init__.py
cadbuildr/foundation/__init__.py
cadbuildr/foundation/exceptions.py
cadbuildr/foundation/finders/__init__.py
cadbuildr/foundation/finders/base.py
cadbuildr/foundation/geometry/__init__.py
cadbuildr/foundation/geometry/frame.py
cadbuildr/foundation/geometry/plane.py
cadbuildr/foundation/geometry/tf_helper.py
cadbuildr/foundation/geometry/transform3d.py
cadbuildr/foundation/interface/__init__.py
cadbuildr/foundation/interface/interface.py
cadbuildr/foundation/operations/__init__.py
cadbuildr/foundation/operations/base.py
cadbuildr/foundation/operations/chamfer.py
cadbuildr/foundation/operations/extrude.py
cadbuildr/foundation/operations/fillet.py
cadbuildr/foundation/operations/grid.py
cadbuildr/foundation/operations/lathe.py
cadbuildr/foundation/operations/loft.py
cadbuildr/foundation/operations/shell.py
cadbuildr/foundation/operations/sweep.py
cadbuildr/foundation/py.typed
cadbuildr/foundation/rendering/__init__.py
cadbuildr/foundation/rendering/material.py
cadbuildr/foundation/scripts/test_screenshot.py
cadbuildr/foundation/sketch/__init__.py
cadbuildr/foundation/sketch/axis.py
cadbuildr/foundation/sketch/base.py
cadbuildr/foundation/sketch/closed_sketch_shape.py
cadbuildr/foundation/sketch/draw.py
cadbuildr/foundation/sketch/pattern.py
cadbuildr/foundation/sketch/point.py
cadbuildr/foundation/sketch/primitives/__init__.py
cadbuildr/foundation/sketch/primitives/arc.py
cadbuildr/foundation/sketch/primitives/line.py
cadbuildr/foundation/sketch/rectangle.py
cadbuildr/foundation/sketch/sketch.py
cadbuildr/foundation/sketch/spline.py
cadbuildr/foundation/sketch/test_arc.py
cadbuildr/foundation/sketch/test_spline.py
cadbuildr/foundation/types/__init__.py
cadbuildr/foundation/types/assembly.py
cadbuildr/foundation/types/comp_or_assy.py
cadbuildr/foundation/types/node.py
cadbuildr/foundation/types/node_children.py
cadbuildr/foundation/types/node_interface.py
cadbuildr/foundation/types/parameterUI.py
cadbuildr/foundation/types/parameters.py
cadbuildr_foundation-0.0.15.dist-info/METADATA
cadbuildr_foundation-0.0.15.dist-info/WHEEL
cadbuildr_foundation-0.0.15.dist-info/RECORD
