Metadata-Version: 2.3
Name: cadbuildr-foundation
Version: 0.0.15
Summary: Python core package for cadbuildr
License: MIT
Keywords: cad,3d,modeling
Author: Clement Jambou
Requires-Python: >=3.10,<4.0
Classifier: Development Status :: 4 - Beta
Classifier: Intended Audience :: Developers
Classifier: License :: OSI Approved :: MIT License
Classifier: Programming Language :: Python :: 3
Classifier: Programming Language :: Python :: 3.10
Classifier: Programming Language :: Python :: 3.11
Classifier: Programming Language :: Python :: 3.12
Classifier: Programming Language :: Python :: 3.13
Classifier: Topic :: Software Development :: Libraries :: Python Modules
Requires-Dist: mypy (>=1.9.0,<2.0.0)
Requires-Dist: numpy (>=1.23.4,<2.0.0)
Requires-Dist: websocket-client (>=1.7.0,<2.0.0)
Project-URL: Homepage, https://cadbuildr.com
Project-URL: Repository, https://github.com/cadbuildr/foundation
